tests/__init__.py
tests/test_thicc.py
thicc/__init__.py
thicc/__main__.py
thicc/thicc.py
thicc-0.0.8.dist-info/LICENSE
thicc-0.0.8.dist-info/METADATA
thicc-0.0.8.dist-info/WHEEL
thicc-0.0.8.dist-info/entry_points.txt
thicc-0.0.8.dist-info/top_level.txt
thicc-0.0.8.dist-info/RECORD
