Metadata-Version: 2.1
Name: thicc
Version: 0.0.8
Summary: thicc - Convert characters to their fullwidth representation
Home-page: https://github.com/t-mart/thicc
Author: Tim Martin
Author-email: tim@timmart.in
License: MIT
Download-URL: https://github.com/t-mart/thicc
Platform: UNKNOWN
